wuerth_hochenburger_ds/__init__.py
wuerth_hochenburger_ds/db/domain/__init__.py
wuerth_hochenburger_ds/db/domain/DWH.py
wuerth_hochenburger_ds/db/domain/vertriebsplanun_ops.py
wuerth_hochenburger_ds/db/standard_queries/__init__.py
wuerth_hochenburger_ds/db/standard_queries/queries.py
wuerth_hochenburger_ds-0.1.0.dist-info/METADATA
wuerth_hochenburger_ds-0.1.0.dist-info/WHEEL
wuerth_hochenburger_ds-0.1.0.dist-info/RECORD
